ethnidata/__init__.py
ethnidata/downloader.py
ethnidata/ethnidata.db
ethnidata/predictor.py
ethnidata/predictor_old.py
ethnidata-3.1.4.dist-info/licenses/LICENSE
ethnidata-3.1.4.dist-info/METADATA
ethnidata-3.1.4.dist-info/WHEEL
ethnidata-3.1.4.dist-info/top_level.txt
ethnidata-3.1.4.dist-info/RECORD
