Metadata-Version: 2.4
Name: ethnidata
Version: 3.1.4
Summary: Predict nationality, ethnicity, gender, region, language and religion from names - 238 countries, 6 major religions, 5.9M+ names, complete religious coverage
Author-email: Teyfik OZ <teyfikoz@example.com>
License: MIT
Project-URL: Homepage, https://github.com/teyfikoz/ethnidata
Project-URL: Documentation, https://github.com/teyfikoz/ethnidata#readme
Project-URL: Repository, https://github.com/teyfikoz/ethnidata.git
Project-URL: Issues, https://github.com/teyfikoz/ethnidata/issues
Keywords: names,nationality,ethnicity,demographics,prediction,NLP
Classifier: Development Status :: 4 - Beta
Classifier: Intended Audience :: Developers
Classifier: Intended Audience :: Science/Research
Classifier: Topic :: Scientific/Engineering :: Information Analysis
Classifier: Programming Language :: Python :: 3
Classifier: Programming Language :: Python :: 3.8
Classifier: Programming Language :: Python :: 3.9
Classifier: Programming Language :: Python :: 3.10
Classifier: Programming Language :: Python :: 3.11
Classifier: Programming Language :: Python :: 3.12
Requires-Python: >=3.8
License-File: LICENSE
Requires-Dist: pycountry>=22.3.5
Requires-Dist: unidecode>=1.3.6
Provides-Extra: dev
Requires-Dist: pytest>=7.0.0; extra == "dev"
Requires-Dist: pytest-cov>=4.0.0; extra == "dev"
Provides-Extra: build
Requires-Dist: requests>=2.31.0; extra == "build"
Requires-Dist: pandas>=2.0.0; extra == "build"
Requires-Dist: numpy>=1.24.0; extra == "build"
Requires-Dist: beautifulsoup4>=4.12.0; extra == "build"
Requires-Dist: lxml>=4.9.0; extra == "build"
Requires-Dist: tqdm>=4.65.0; extra == "build"
Requires-Dist: wikipedia-api>=0.6.0; extra == "build"
Requires-Dist: sqlalchemy>=2.0.0; extra == "build"
Dynamic: license-file
